tflens/__init__.py
tflens/__main__.py
tflens/controller/__init__.py
tflens/controller/tfstate.py
tflens/exception/__init__.py
tflens/exception/exception.py
tflens/helper/__init__.py
tflens/helper/config.py
tflens/helper/filter.py
tflens/helper/location.py
tflens/helper/remote.py
tflens/helper/table.py
tflens/model/__init__.py
tflens/model/tfstate.py
tflens/model/tfstate_resource.py
tflens/service/__init__.py
tflens/service/tfstate.py
tflens-1.5.0.dist-info/LICENSE
tflens-1.5.0.dist-info/METADATA
tflens-1.5.0.dist-info/WHEEL
tflens-1.5.0.dist-info/entry_points.txt
tflens-1.5.0.dist-info/top_level.txt
tflens-1.5.0.dist-info/RECORD
