Metadata-Version: 2.1
Name: tflens
Version: 1.5.0
Summary: Terraform state viewer
Home-page: https://github.com/neovasili/tflens
Author: Juan Manuel Ruiz Fernández
License: UNKNOWN
Keywords: terraform viewer state tfstate cli
Platform: UNKNOWN
Classifier: Development Status :: 5 - Production/Stable
Classifier: Environment :: Console
Classifier: Intended Audience :: Developers
Classifier: License :: OSI Approved :: MIT License
Classifier: Natural Language :: English
Classifier: Operating System :: OS Independent
Classifier: Programming Language :: Python :: 3
Classifier: Topic :: Software Development :: Documentation
Classifier: Topic :: Terminals
Requires-Python: >=3.6
License-File: LICENSE
